masced_bandits/__init__.py
masced_bandits/bandit_options.py
masced_bandits/utilities.py
masced_bandits/bandits/Bandit.py
masced_bandits/bandits/DUCB.py
masced_bandits/bandits/ETC.py
masced_bandits/bandits/EXP3.py
masced_bandits/bandits/EXP3S.py
masced_bandits/bandits/EXP4.py
masced_bandits/bandits/EwS.py
masced_bandits/bandits/Expert.py
masced_bandits/bandits/SWUCB.py
masced_bandits/bandits/UCB.py
masced_bandits/bandits/UCBImproved.py
masced_bandits/bandits/__init__.py
masced_bandits/bandits/egreedy.py
masced_bandits_EGAlberts-0.0.1.dist-info/LICENSE
masced_bandits_EGAlberts-0.0.1.dist-info/METADATA
masced_bandits_EGAlberts-0.0.1.dist-info/WHEEL
masced_bandits_EGAlberts-0.0.1.dist-info/top_level.txt
masced_bandits_EGAlberts-0.0.1.dist-info/RECORD
