Metadata-Version: 2.1
Name: masced-bandits-EGAlberts
Version: 0.0.1
Summary: bandit algs
Home-page: https://github.com/EGAlberts/
Author: Elvin Alberts
Author-email: elvingalberts@gmail.com
Classifier: Programming Language :: Python :: 3.7
Classifier: License :: OSI Approved :: MIT License
Classifier: Operating System :: OS Independent
Requires-Python: >=3.0
License-File: LICENSE
